neural/neural.py
neural/__init__.py
neural-0.1.0.dist-info/DESCRIPTION.rst
neural-0.1.0.dist-info/METADATA
neural-0.1.0.dist-info/metadata.json
neural-0.1.0.dist-info/RECORD
neural-0.1.0.dist-info/top_level.txt
neural-0.1.0.dist-info/WHEEL
