Metadata-Version: 1.1
Name: neural
Version: 0.1.0
Summary: Simple neural network implementation in Python based on Andrew Ng's Machine Learning online course.
Home-page: https://github.com/pqn/neural
Author: Prem Nair
Author-email: prem.q.nair@gmail.com
License: BSD
Keywords: neural
Platform: UNKNOWN
Classifier: Development Status :: 2 - Pre-Alpha
Classifier: Intended Audience :: Developers
Classifier: License :: OSI Approved :: BSD License
Classifier: Natural Language :: English
Classifier: Programming Language :: Python :: 2
Classifier: Programming Language :: Python :: 2.6
Classifier: Programming Language :: Python :: 2.7
Classifier: Programming Language :: Python :: 3
Classifier: Programming Language :: Python :: 3.3
